drf_common_exceptions/__init__.py
drf_common_exceptions/handlers.py
drf_common_exceptions/utils.py
drf_common_exceptions_shabbir20-0.1.3.dist-info/licenses/LICENSE
drf_common_exceptions_shabbir20-0.1.3.dist-info/METADATA
drf_common_exceptions_shabbir20-0.1.3.dist-info/WHEEL
drf_common_exceptions_shabbir20-0.1.3.dist-info/top_level.txt
drf_common_exceptions_shabbir20-0.1.3.dist-info/RECORD
